djenga/__init__.py
djenga/animal_pairs/__init__.py
djenga/animal_pairs/dictionary.py
djenga/animal_pairs/utils.py
djenga/cache/__init__.py
djenga/celery/__init__.py
djenga/celery/backends.py
djenga/celery/results.py
djenga/celery/tasks.py
djenga/celery/utils.py
djenga/core/__init__.py
djenga/core/bunch.py
djenga/core/env.py
djenga/csv/__init__.py
djenga/csv/unicode_csv_reader.py
djenga/csv/unicode_csv_writer.py
djenga/currency/__init__.py
djenga/currency/rounding.py
djenga/dateutil/__init__.py
djenga/dateutil/basic_functions.py
djenga/db/__init__.py
djenga/db/uuidfield.py
djenga/db/lazy_mysql_client/__init__.py
djenga/db/lazy_mysql_client/base.py
djenga/db/lazy_mysql_client/client.py
djenga/db/lazy_mysql_connector/__init__.py
djenga/db/lazy_mysql_connector/base.py
djenga/db/lazy_mysql_connector/client.py
djenga/email/__init__.py
djenga/email/helpers.py
djenga/encryption/__init__.py
djenga/encryption/gcm.py
djenga/encryption/helpers.py
djenga/encryption/kms.py
djenga/encryption/kms_wrap.py
djenga/encryption/kms_wrapped.py
djenga/exceptions/__init__.py
djenga/exceptions/traceback.py
djenga/inlinecss/__init__.py
djenga/loggers/__init__.py
djenga/loggers/filters.py
djenga/loggers/util.py
djenga/logging/__init__.py
djenga/logging/formatters.py
djenga/management/__init__.py
djenga/management/commands/__init__.py
djenga/management/commands/animal_pairs.py
djenga/management/commands/clean_command_output.py
djenga/management/commands/commandlogginglevels.py
djenga/management/commands/configurationmixin.py
djenga/management/commands/csvmixin.py
djenga/management/commands/debug_celery.py
djenga/management/commands/emailcommand.py
djenga/management/commands/inputcsvmixin.py
djenga/management/commands/run_integration_tests.py
djenga/management/commands/statuscommand.py
djenga/migrations/0001_initial.py
djenga/migrations/0002_management_command_help.py
djenga/migrations/__init__.py
djenga/mixins/__init__.py
djenga/mixins/jsonmixin.py
djenga/mixins/loggingmixin.py
djenga-1.0.8.dist-info/LICENSE
djenga-1.0.8.dist-info/METADATA
djenga-1.0.8.dist-info/WHEEL
djenga-1.0.8.dist-info/entry_points.txt
djenga-1.0.8.dist-info/top_level.txt
djenga-1.0.8.dist-info/zip-safe
djenga-1.0.8.dist-info/RECORD
