Metadata-Version: 2.1
Name: djenga
Version: 1.0.8
Summary: Useful building blocks for Django.
Home-page: https://github.com/2ps/djenga
Author: Preetam Shingavi
Author-email: p.shingavi@yahoo.com
License: BSD
Keywords: django python
Platform: UNKNOWN
Classifier: Development Status :: 5 - Production/Stable
Classifier: Intended Audience :: Developers
Classifier: Topic :: Software Development :: Libraries :: Python Modules
Classifier: Programming Language :: Python :: 3
Classifier: Programming Language :: Python :: 3.6
Classifier: Framework :: Django
Classifier: Framework :: Django :: 1.11
Classifier: Framework :: Django :: 1.10
Classifier: Framework :: Django :: 1.9
Classifier: License :: OSI Approved :: BSD License
Requires-Dist: six (>=1.10.0)
Requires-Dist: Django (>=1.9)
Requires-Dist: cssutils (>=1.0)
Requires-Dist: beautifulsoup4 (>=4.3.2)
Requires-Dist: pynliner (>=0.8.0)
Requires-Dist: pycryptodome (>=3.6.6)
Requires-Dist: pytz
Requires-Dist: python-dateutil
Requires-Dist: pyyaml
Requires-Dist: django-redis-cache
Requires-Dist: celery (>=4.1.0)
Requires-Dist: boto3
Requires-Dist: requests (>=2.19)
